{
  "AppearanceHead" : 22,
  "AppearanceType" : 6,
  "ArmorPartRFoot" : 1,
  "BodyBag" : 0,
  "BodyPartBelt" : 0,
  "BodyPartLBicep" : 1,
  "BodyPartLFArm" : 1,
  "BodyPartLFoot" : 1,
  "BodyPartLHand" : 1,
  "BodyPartLShin" : 1,
  "BodyPartLShoul" : 0,
  "BodyPartLThigh" : 1,
  "BodyPartNeck" : 1,
  "BodyPartPelvis" : 1,
  "BodyPartRBicep" : 1,
  "BodyPartRFArm" : 1,
  "BodyPartRHand" : 1,
  "BodyPartRShin" : 1,
  "BodyPartRShoul" : 0,
  "BodyPartRThigh" : 1,
  "BodyPartTorso" : 1,
  "CRAdjust" : 0,
  "Cha" : 14,
  "ChallengeRating" : 18.0,
  "ClassList" : [
    {
      "ClassLevel" : 25,
      "ClassX" : 2,
      "MemorizedList1" : [
        {
          "Spell" : 6,
          "SpellFlags" : 1,
          "SpellMetaMagic" : 0
        },
        {
          "Spell" : 32,
          "SpellFlags" : 1,
          "SpellMetaMagic" : 0
        },
        {
          "Spell" : 32,
          "SpellFlags" : 1,
          "SpellMetaMagic" : 0
        },
        {
          "Spell" : 32,
          "SpellFlags" : 1,
          "SpellMetaMagic" : 0
        },
        {
          "Spell" : 32,
          "SpellFlags" : 1,
          "SpellMetaMagic" : 0
        },
        {
          "Spell" : 32,
          "SpellFlags" : 1,
          "SpellMetaMagic" : 0
        },
        {
          "Spell" : 32,
          "SpellFlags" : 1,
          "SpellMetaMagic" : 0
        },
        {
          "Spell" : 32,
          "SpellFlags" : 1,
          "SpellMetaMagic" : 0
        }
      ],
      "MemorizedList2" : [
        {
          "Spell" : 1,
          "SpellFlags" : 1,
          "SpellMetaMagic" : 0
        },
        {
          "Spell" : 34,
          "SpellFlags" : 1,
          "SpellMetaMagic" : 0
        },
        {
          "Spell" : 34,
          "SpellFlags" : 1,
          "SpellMetaMagic" : 0
        },
        {
          "Spell" : 34,
          "SpellFlags" : 1,
          "SpellMetaMagic" : 0
        },
        {
          "Spell" : 34,
          "SpellFlags" : 1,
          "SpellMetaMagic" : 0
        },
        {
          "Spell" : 34,
          "SpellFlags" : 1,
          "SpellMetaMagic" : 0
        }
      ],
      "MemorizedList3" : [
        {
          "Spell" : 4,
          "SpellFlags" : 1,
          "SpellMetaMagic" : 0
        },
        {
          "Spell" : 35,
          "SpellFlags" : 1,
          "SpellMetaMagic" : 0
        },
        {
          "Spell" : 35,
          "SpellFlags" : 1,
          "SpellMetaMagic" : 0
        },
        {
          "Spell" : 41,
          "SpellFlags" : 1,
          "SpellMetaMagic" : 0
        },
        {
          "Spell" : 91,
          "SpellFlags" : 1,
          "SpellMetaMagic" : 0
        },
        {
          "Spell" : 145,
          "SpellFlags" : 1,
          "SpellMetaMagic" : 0
        },
        {
          "Spell" : 147,
          "SpellFlags" : 1,
          "SpellMetaMagic" : 0
        }
      ],
      "MemorizedList4" : [
        {
          "Spell" : 31,
          "SpellFlags" : 1,
          "SpellMetaMagic" : 0
        },
        {
          "Spell" : 40,
          "SpellFlags" : 1,
          "SpellMetaMagic" : 0
        },
        {
          "Spell" : 42,
          "SpellFlags" : 1,
          "SpellMetaMagic" : 0
        },
        {
          "Spell" : 62,
          "SpellFlags" : 1,
          "SpellMetaMagic" : 0
        },
        {
          "Spell" : 76,
          "SpellFlags" : 1,
          "SpellMetaMagic" : 0
        },
        {
          "Spell" : 76,
          "SpellFlags" : 1,
          "SpellMetaMagic" : 0
        },
        {
          "Spell" : 76,
          "SpellFlags" : 1,
          "SpellMetaMagic" : 0
        }
      ],
      "MemorizedList5" : [
        {
          "Spell" : 19,
          "SpellFlags" : 1,
          "SpellMetaMagic" : 0
        },
        {
          "Spell" : 61,
          "SpellFlags" : 1,
          "SpellMetaMagic" : 0
        },
        {
          "Spell" : 80,
          "SpellFlags" : 1,
          "SpellMetaMagic" : 0
        },
        {
          "Spell" : 164,
          "SpellFlags" : 1,
          "SpellMetaMagic" : 0
        },
        {
          "Spell" : 168,
          "SpellFlags" : 1,
          "SpellMetaMagic" : 0
        },
        {
          "Spell" : 186,
          "SpellFlags" : 1,
          "SpellMetaMagic" : 0
        }
      ],
      "MemorizedList6" : [
        {
          "Spell" : 5,
          "SpellFlags" : 1,
          "SpellMetaMagic" : 0
        },
        {
          "Spell" : 28,
          "SpellFlags" : 1,
          "SpellMetaMagic" : 0
        },
        {
          "Spell" : 30,
          "SpellFlags" : 1,
          "SpellMetaMagic" : 0
        },
        {
          "Spell" : 67,
          "SpellFlags" : 1,
          "SpellMetaMagic" : 0
        },
        {
          "Spell" : 79,
          "SpellFlags" : 1,
          "SpellMetaMagic" : 0
        },
        {
          "Spell" : 79,
          "SpellFlags" : 1,
          "SpellMetaMagic" : 0
        }
      ],
      "MemorizedList7" : [
        {
          "Spell" : 366,
          "SpellFlags" : 1,
          "SpellMetaMagic" : 0
        },
        {
          "Spell" : 366,
          "SpellFlags" : 1,
          "SpellMetaMagic" : 0
        },
        {
          "Spell" : 70,
          "SpellFlags" : 1,
          "SpellMetaMagic" : 0
        },
        {
          "Spell" : 374,
          "SpellFlags" : 1,
          "SpellMetaMagic" : 0
        },
        {
          "Spell" : 194,
          "SpellFlags" : 1,
          "SpellMetaMagic" : 0
        }
      ],
      "MemorizedList8" : [
        {
          "Spell" : 29,
          "SpellFlags" : 1,
          "SpellMetaMagic" : 0
        },
        {
          "Spell" : 57,
          "SpellFlags" : 1,
          "SpellMetaMagic" : 0
        },
        {
          "Spell" : 114,
          "SpellFlags" : 1,
          "SpellMetaMagic" : 0
        },
        {
          "Spell" : 182,
          "SpellFlags" : 1,
          "SpellMetaMagic" : 0
        },
        {
          "Spell" : 183,
          "SpellFlags" : 1,
          "SpellMetaMagic" : 0
        }
      ],
      "MemorizedList9" : [
        {
          "Spell" : 51,
          "SpellFlags" : 1,
          "SpellMetaMagic" : 0
        },
        {
          "Spell" : 63,
          "SpellFlags" : 1,
          "SpellMetaMagic" : 0
        },
        {
          "Spell" : 87,
          "SpellFlags" : 1,
          "SpellMetaMagic" : 0
        },
        {
          "Spell" : 173,
          "SpellFlags" : 1,
          "SpellMetaMagic" : 0
        },
        {
          "Spell" : 178,
          "SpellFlags" : 1,
          "SpellMetaMagic" : 0
        }
      ]
    }
  ],
  "ColorHair" : 16,
  "ColorSkin" : 1,
  "ColorTattoo1" : 1,
  "ColorTattoo2" : 1,
  "Comment" : "",
  "Con" : 14,
  "Conversation" : "pepin001",
  "CurrentHitPoints" : 116,
  "DecayTime" : 5000,
  "Deity" : "",
  "Description" : null,
  "Dex" : 8,
  "Disarmable" : 1,
  "EquipItemList" : [
    {
      "EquippedRes" : "item020",
      "StructId" : 2
    }
  ],
  "FactionID" : 3,
  "FeatList" : [
    {
      "Feat" : 2
    },
    {
      "Feat" : 3
    },
    {
      "Feat" : 4
    },
    {
      "Feat" : 13
    },
    {
      "Feat" : 318
    },
    {
      "Feat" : 258
    },
    {
      "Feat" : 29
    },
    {
      "Feat" : 32
    },
    {
      "Feat" : 35
    },
    {
      "Feat" : 166
    },
    {
      "Feat" : 167
    },
    {
      "Feat" : 168
    },
    {
      "Feat" : 169
    },
    {
      "Feat" : 170
    },
    {
      "Feat" : 171
    },
    {
      "Feat" : 172
    },
    {
      "Feat" : 322
    },
    {
      "Feat" : 294
    },
    {
      "Feat" : 46
    }
  ],
  "FirstName" : "Pepin the Healer",
  "Fortbonus" : 0,
  "Gender" : 0,
  "GoodEvil" : 50,
  "HitPoints" : 116,
  "Int" : 10,
  "Interruptable" : 1,
  "IsImmortal" : 0,
  "IsPC" : 0,
  "ItemList" : [
    {
      "InventoryRes" : "nw_it_torch001",
      "ReposPosX" : 0,
      "ReposPosy" : 0
    },
    {
      "InventoryRes" : "nw_it_mpotion001",
      "ReposPosX" : 1,
      "ReposPosy" : 0
    },
    {
      "InventoryRes" : "nw_it_mpotion001",
      "ReposPosX" : 2,
      "ReposPosy" : 0
    },
    {
      "InventoryRes" : "nw_it_mpotion001",
      "ReposPosX" : 3,
      "ReposPosy" : 0
    }
  ],
  "LastName" : "",
  "LawfulChaotic" : 50,
  "Lootable" : 0,
  "MaxHitPoints" : 166,
  "NaturalAC" : 0,
  "NoPermDeath" : 1,
  "PaletteID" : 44,
  "PerceptionRange" : 11,
  "Phenotype" : 0,
  "Plot" : 1,
  "PortraitId" : 115,
  "Race" : 6,
  "Refbonus" : 0,
  "ScriptAttacked" : "nw_c2_default5",
  "ScriptDamaged" : "nw_c2_default6",
  "ScriptDeath" : "nw_c2_default7",
  "ScriptDialogue" : "nw_c2_default4",
  "ScriptDisturbed" : "nw_c2_default8",
  "ScriptEndRound" : "nw_c2_default3",
  "ScriptHeartbeat" : "nw_c2_default1",
  "ScriptOnBlocked" : "nw_c2_defaulte",
  "ScriptOnNotice" : "nw_c2_default2",
  "ScriptRested" : "nw_c2_defaulta",
  "ScriptSpawn" : "nw_c2_default9",
  "ScriptSpellAt" : "nw_c2_defaultb",
  "ScriptUserDefine" : "nw_c2_defaultd",
  "SkillList" : [
    {
      "Rank" : 0
    },
    {
      "Rank" : 26
    },
    {
      "Rank" : 0
    },
    {
      "Rank" : 0
    },
    {
      "Rank" : 26
    },
    {
      "Rank" : 0
    },
    {
      "Rank" : 0
    },
    {
      "Rank" : 2
    },
    {
      "Rank" : 0
    },
    {
      "Rank" : 0
    },
    {
      "Rank" : 26
    },
    {
      "Rank" : 0
    },
    {
      "Rank" : 2
    },
    {
      "Rank" : 0
    },
    {
      "Rank" : 0
    },
    {
      "Rank" : 0
    },
    {
      "Rank" : 2
    },
    {
      "Rank" : 0
    },
    {
      "Rank" : 0
    },
    {
      "Rank" : 0
    },
    {
      "Rank" : 0
    },
    {
      "Rank" : 0
    },
    {
      "Rank" : 0
    },
    {
      "Rank" : 0
    },
    {
      "Rank" : 0
    },
    {
      "Rank" : 0
    },
    {
      "Rank" : 0
    }
  ],
  "SoundSetFile" : 65535,
  "SpecAbilityList" : [ ],
  "StartingPackage" : 2,
  "Str" : 14,
  "Subrace" : "",
  "Tag" : "NPC_PEPIN",
  "Tail" : 0,
  "TemplateList" : [ ],
  "TemplateResRef" : "pepinthehealer",
  "WalkRate" : 4,
  "Willbonus" : 0,
  "Wings" : 0,
  "Wis" : 22
}