{
  "Active" : 1,
  "Comment" : "",
  "CreatureList" : [
    {
      "Appearance" : 1246,
      "CR" : 0.33333334,
      "ResRef" : "worm001",
      "SingleSpawn" : 0
    },
    {
      "Appearance" : 1246,
      "CR" : 1.0,
      "ResRef" : "giantworm",
      "SingleSpawn" : 0
    }
  ],
  "Difficulty" : 0,
  "DifficultyIndex" : 1,
  "Faction" : 1,
  "LocalizedName" : "Ant Group (low)",
  "MaxCreatures" : 6,
  "OnEntered" : "",
  "OnExhausted" : "",
  "OnExit" : "",
  "OnHeartbeat" : "",
  "OnUserDefined" : "",
  "PaletteID" : 2,
  "PlayerOnly" : 1,
  "RecCreatures" : 4,
  "Reset" : 1,
  "ResetTime" : 1200,
  "Respawns" : -1,
  "SpawnOption" : 1,
  "Tag" : "AntGrouplow",
  "TemplateResRef" : "blueprint042"
}