{
  "Active" : 1,
  "Comment" : "",
  "CreatureList" : [
    {
      "Appearance" : 6,
      "CR" : 18.0,
      "ResRef" : "sucubus003",
      "SingleSpawn" : 1
    },
    {
      "Appearance" : 6,
      "CR" : 20.0,
      "ResRef" : "sucubus004",
      "SingleSpawn" : 1
    },
    {
      "Appearance" : 6,
      "CR" : 23.0,
      "ResRef" : "magii004",
      "SingleSpawn" : 0
    },
    {
      "Appearance" : 5,
      "CR" : 21.0,
      "ResRef" : "knight004",
      "SingleSpawn" : 0
    },
    {
      "Appearance" : 5,
      "CR" : 23.0,
      "ResRef" : "knight005",
      "SingleSpawn" : 1
    }
  ],
  "Difficulty" : 0,
  "DifficultyIndex" : 3,
  "Faction" : 1,
  "LocalizedName" : "Endgame (first)",
  "MaxCreatures" : 6,
  "OnEntered" : "",
  "OnExhausted" : "",
  "OnExit" : "",
  "OnHeartbeat" : "",
  "OnUserDefined" : "",
  "PaletteID" : 4,
  "PlayerOnly" : 1,
  "RecCreatures" : 4,
  "Reset" : 1,
  "ResetTime" : 1800,
  "Respawns" : -1,
  "SpawnOption" : 0,
  "Tag" : "Endgamefirst",
  "TemplateResRef" : "blueprint033"
}