{
  "AddCost" : 0,
  "BaseItem" : 73,
  "Charges" : 0,
  "Cost" : 4556250,
  "Cursed" : 0,
  "DescIdentified" : null,
  "Description" : null,
  "Identified" : 0,
  "LocalizedName" : "Lich Skin",
  "ModelPart1" : 1,
  "PaletteID" : 14,
  "Plot" : 0,
  "PropertiesList" : [
    {
      "ChanceAppear" : 100,
      "CostTable" : 1,
      "CostValue" : 2,
      "Param1" : 255,
      "Param1Value" : 255,
      "PropertyName" : 0,
      "Subtype" : 5
    },
    {
      "ChanceAppear" : 100,
      "CostTable" : 1,
      "CostValue" : 2,
      "Param1" : 255,
      "Param1Value" : 255,
      "PropertyName" : 0,
      "Subtype" : 3
    },
    {
      "ChanceAppear" : 100,
      "CostTable" : 1,
      "CostValue" : 2,
      "Param1" : 255,
      "Param1Value" : 255,
      "PropertyName" : 0,
      "Subtype" : 4
    },
    {
      "ChanceAppear" : 100,
      "CostTable" : 6,
      "CostValue" : 5,
      "Param1" : 255,
      "Param1Value" : 0,
      "PropertyName" : 22,
      "Subtype" : 1
    },
    {
      "ChanceAppear" : 100,
      "CostTable" : 5,
      "CostValue" : 7,
      "Param1" : 255,
      "Param1Value" : 255,
      "PropertyName" : 20,
      "Subtype" : 7
    },
    {
      "ChanceAppear" : 100,
      "CostTable" : 5,
      "CostValue" : 7,
      "Param1" : 255,
      "Param1Value" : 255,
      "PropertyName" : 20,
      "Subtype" : 9
    },
    {
      "ChanceAppear" : 100,
      "CostTable" : 0,
      "CostValue" : 0,
      "Param1" : 255,
      "Param1Value" : 255,
      "PropertyName" : 37,
      "Subtype" : 8
    },
    {
      "ChanceAppear" : 100,
      "CostTable" : 0,
      "CostValue" : 0,
      "Param1" : 255,
      "Param1Value" : 255,
      "PropertyName" : 37,
      "Subtype" : 4
    },
    {
      "ChanceAppear" : 100,
      "CostTable" : 0,
      "CostValue" : 0,
      "Param1" : 255,
      "Param1Value" : 255,
      "PropertyName" : 37,
      "Subtype" : 1
    },
    {
      "ChanceAppear" : 100,
      "CostTable" : 0,
      "CostValue" : 0,
      "Param1" : 255,
      "Param1Value" : 255,
      "PropertyName" : 37,
      "Subtype" : 2
    },
    {
      "ChanceAppear" : 100,
      "CostTable" : 0,
      "CostValue" : 0,
      "Param1" : 255,
      "Param1Value" : 255,
      "PropertyName" : 37,
      "Subtype" : 7
    },
    {
      "ChanceAppear" : 100,
      "CostTable" : 0,
      "CostValue" : 0,
      "Param1" : 255,
      "Param1Value" : 255,
      "PropertyName" : 37,
      "Subtype" : 3
    },
    {
      "ChanceAppear" : 100,
      "CostTable" : 0,
      "CostValue" : 0,
      "Param1" : 255,
      "Param1Value" : 0,
      "PropertyName" : 37,
      "Subtype" : 0
    },
    {
      "ChanceAppear" : 100,
      "CostTable" : 1,
      "CostValue" : 7,
      "Param1" : 255,
      "Param1Value" : 255,
      "PropertyName" : 73,
      "Subtype" : 0
    }
  ],
  "StackSize" : 1,
  "Stolen" : 0,
  "Tag" : "NW_CREITEMLIC",
  "TemplateResRef" : "creitemlic001"
}