{
  "AddCost" : 0,
  "BaseItem" : 55,
  "Charges" : 0,
  "Comment" : "1",
  "Cost" : 1596160,
  "Cursed" : 0,
  "DescIdentified" : {
    "StringRef" : 13213,
    "Strings" : [ ]
  },
  "Description" : null,
  "Identified" : 1,
  "LocalizedName" : {
    "StringRef" : 14232,
    "Strings" : [
      {
        "Id" : 0,
        "String" : "Death Clan Scythe"
      }
    ]
  },
  "ModelPart1" : 24,
  "ModelPart2" : 34,
  "ModelPart3" : 34,
  "PaletteID" : 3,
  "Plot" : 0,
  "PropertiesList" : [
    {
      "ChanceAppear" : 100,
      "CostTable" : 4,
      "CostValue" : 25,
      "Param1" : 255,
      "Param1Value" : 0,
      "PropertyName" : 16,
      "Subtype" : 1
    },
    {
      "ChanceAppear" : 100,
      "CostTable" : 2,
      "CostValue" : 7,
      "Param1" : 255,
      "Param1Value" : 255,
      "PropertyName" : 6,
      "Subtype" : 0
    },
    {
      "ChanceAppear" : 100,
      "CostTable" : 0,
      "CostValue" : 0,
      "Param1" : 255,
      "Param1Value" : 0,
      "PropertyName" : 43,
      "Subtype" : 0
    },
    {
      "ChanceAppear" : 100,
      "CostTable" : 24,
      "CostValue" : 2,
      "Param1" : 255,
      "Param1Value" : 0,
      "PropertyName" : 48,
      "Subtype" : 25
    }
  ],
  "StackSize" : 1,
  "Stolen" : 0,
  "Tag" : "D1_DEATHCLANSCYTHE",
  "TemplateResRef" : "deathclansscythe"
}