{
  "AddCost" : 0,
  "ArmorPartBelt" : 3,
  "ArmorPartLBicep" : 1,
  "ArmorPartLFArm" : 4,
  "ArmorPartLFoot" : 5,
  "ArmorPartLHand" : 7,
  "ArmorPartLShin" : 6,
  "ArmorPartLShoul" : 7,
  "ArmorPartLThigh" : 5,
  "ArmorPartNeck" : 1,
  "ArmorPartPelvis" : 6,
  "ArmorPartRBicep" : 1,
  "ArmorPartRFArm" : 4,
  "ArmorPartRFoot" : 5,
  "ArmorPartRHand" : 7,
  "ArmorPartRShin" : 6,
  "ArmorPartRShoul" : 7,
  "ArmorPartRThigh" : 5,
  "ArmorPartRobe" : 0,
  "ArmorPartTorso" : 47,
  "BaseItem" : 16,
  "Charges" : 0,
  "Cloth1Color" : 47,
  "Cloth2Color" : 46,
  "Cost" : 23257,
  "Cursed" : 0,
  "DescIdentified" : null,
  "Description" : "",
  "Identified" : 0,
  "Leather1Color" : 46,
  "Leather2Color" : 46,
  "LocalizedName" : "Iceblink",
  "Metal1Color" : 37,
  "Metal2Color" : 39,
  "PaletteID" : 8,
  "Plot" : 0,
  "PropertiesList" : [
    {
      "ChanceAppear" : 100,
      "CostTable" : 2,
      "CostValue" : 3,
      "Param1" : 255,
      "Param1Value" : 0,
      "PropertyName" : 1,
      "Subtype" : 0
    },
    {
      "ChanceAppear" : 100,
      "CostTable" : 7,
      "CostValue" : 3,
      "Param1" : 255,
      "Param1Value" : 0,
      "PropertyName" : 23,
      "Subtype" : 7
    },
    {
      "ChanceAppear" : 100,
      "CostTable" : 18,
      "CostValue" : 4,
      "Param1" : 9,
      "Param1Value" : 6,
      "PropertyName" : 44,
      "Subtype" : 0
    },
    {
      "ChanceAppear" : 100,
      "CostTable" : 26,
      "CostValue" : 4,
      "Param1" : 255,
      "Param1Value" : 0,
      "PropertyName" : 82,
      "Subtype" : 10
    }
  ],
  "StackSize" : 1,
  "Stolen" : 1,
  "Tag" : "D2_ICEBLINK",
  "TemplateResRef" : "iceblink"
}