{
  "AddCost" : 0,
  "BaseItem" : 40,
  "Charges" : 0,
  "Comment" : "1",
  "Cost" : 1622,
  "Cursed" : 0,
  "DescIdentified" : {
    "StringRef" : 13213,
    "Strings" : [ ]
  },
  "Description" : null,
  "Identified" : 1,
  "LocalizedName" : {
    "StringRef" : 14248,
    "Strings" : [ ]
  },
  "ModelPart1" : 11,
  "ModelPart2" : 12,
  "ModelPart3" : 11,
  "PaletteID" : 54,
  "Plot" : 1,
  "PropertiesList" : [
    {
      "ChanceAppear" : 100,
      "CostTable" : 2,
      "CostValue" : 1,
      "Param1" : 255,
      "Param1Value" : 255,
      "PropertyName" : 6,
      "Subtype" : 0
    }
  ],
  "StackSize" : 1,
  "Stolen" : 0,
  "Tag" : "D1_MELLOKAMA",
  "TemplateResRef" : "mellokama"
}