{
  "AddCost" : 0,
  "BaseItem" : 17,
  "Charges" : 0,
  "Cloth1Color" : 3,
  "Cloth2Color" : 52,
  "Cost" : 27565,
  "Cursed" : 0,
  "DescIdentified" : "The helm was originally King Leoric's war crown, forged by the blacksmith Griswold and given to the King as a gift.  Its visage is now as twisted and evil as the soul of the fallen king.",
  "Description" : "",
  "Identified" : 0,
  "Leather1Color" : 45,
  "Leather2Color" : 52,
  "LocalizedName" : "The Undead Crown",
  "Metal1Color" : 25,
  "Metal2Color" : 24,
  "ModelPart1" : 26,
  "PaletteID" : 54,
  "Plot" : 0,
  "PropertiesList" : [
    {
      "ChanceAppear" : 100,
      "CostTable" : 2,
      "CostValue" : 2,
      "Param1" : 255,
      "Param1Value" : 0,
      "PropertyName" : 4,
      "Subtype" : 24
    },
    {
      "ChanceAppear" : 100,
      "CostTable" : 18,
      "CostValue" : 4,
      "Param1" : 9,
      "Param1Value" : 3,
      "PropertyName" : 44,
      "Subtype" : 0
    },
    {
      "ChanceAppear" : 100,
      "CostTable" : 2,
      "CostValue" : 2,
      "Param1" : 255,
      "Param1Value" : 0,
      "PropertyName" : 51,
      "Subtype" : 0
    }
  ],
  "StackSize" : 1,
  "Stolen" : 1,
  "Tag" : "D1_UNDEADCROWN",
  "TemplateResRef" : "undeadcrown"
}