{
  "AddCost" : 0,
  "BaseItem" : 22,
  "Charges" : 0,
  "Comment" : "1",
  "Cost" : 792024,
  "Cursed" : 0,
  "DescIdentified" : {
    "StringRef" : 14308,
    "Strings" : [
      {
        "Id" : 0,
        "String" : "Damien Oneknife, an assassin of great skill who traveled the breadth of Faerun to claim his targets, refused only one quest.  A man known only as the Dockman, sent him against the legendary Drizzt.  Damien knew he was not the equal of the famed drow warrior and declined.  The next day Damien received this dagger from the Dockman as a gift with a gentle request to reconsider the offer.  His facilities clouded by the dagger, Damien accepted the offer.  He died, never even reaching Drizzt himself, but falling instead to the ranger's loyal companions."
      }
    ]
  },
  "Description" : "",
  "Identified" : 0,
  "LocalizedName" : {
    "StringRef" : 14309,
    "Strings" : [
      {
        "Id" : 0,
        "String" : "Risktaker"
      }
    ]
  },
  "ModelPart1" : 41,
  "ModelPart2" : 51,
  "ModelPart3" : 61,
  "PaletteID" : 34,
  "Plot" : 0,
  "PropertiesList" : [
    {
      "ChanceAppear" : 100,
      "CostTable" : 21,
      "CostValue" : 4,
      "Param1" : 255,
      "Param1Value" : 0,
      "PropertyName" : 27,
      "Subtype" : 3
    },
    {
      "ChanceAppear" : 100,
      "CostTable" : 21,
      "CostValue" : 4,
      "Param1" : 255,
      "Param1Value" : 0,
      "PropertyName" : 27,
      "Subtype" : 4
    },
    {
      "ChanceAppear" : 100,
      "CostTable" : 2,
      "CostValue" : 8,
      "Param1" : 255,
      "Param1Value" : 255,
      "PropertyName" : 6,
      "Subtype" : 0
    },
    {
      "ChanceAppear" : 100,
      "CostTable" : 0,
      "CostValue" : 0,
      "Param1" : 255,
      "Param1Value" : 0,
      "PropertyName" : 35,
      "Subtype" : 0
    },
    {
      "ChanceAppear" : 100,
      "CostTable" : 25,
      "CostValue" : 10,
      "Param1" : 255,
      "Param1Value" : 0,
      "PropertyName" : 52,
      "Subtype" : 5
    },
    {
      "ChanceAppear" : 100,
      "CostTable" : 25,
      "CostValue" : 10,
      "Param1" : 255,
      "Param1Value" : 0,
      "PropertyName" : 52,
      "Subtype" : 8
    },
    {
      "ChanceAppear" : 100,
      "CostTable" : 0,
      "CostValue" : 0,
      "Param1" : 255,
      "Param1Value" : 0,
      "PropertyName" : 63,
      "Subtype" : 8
    }
  ],
  "StackSize" : 1,
  "Stolen" : 0,
  "Tag" : "RISKTAKER",
  "TemplateResRef" : "wswmdg007"
}