{
  "DelayEntry" : 0,
  "DelayReply" : 0,
  "EndConverAbort" : "",
  "EndConversation" : "",
  "EntryList" : [
    {
      "AnimLoop" : 1,
      "Animation" : 40,
      "Delay" : 4294967295,
      "RepliesList" : [ ],
      "Text" : "Why hello!  Are you also looking for books to read?"
    },
    {
      "AnimLoop" : 1,
      "Animation" : 39,
      "Delay" : 4294967295,
      "RepliesList" : [ ],
      "Text" : "Have you seen the books in Cain's shelves?  I can't understand half of them!"
    },
    {
      "AnimLoop" : 1,
      "Animation" : 40,
      "Delay" : 4294967295,
      "RepliesList" : [ ],
      "Text" : "Sorry, I don't give out quests."
    },
    {
      "AnimLoop" : 1,
      "Animation" : 40,
      "Delay" : 4294967295,
      "RepliesList" : [ ],
      "Text" : "Damn, someone put an adult book in the bookshelves again... perverts!"
    },
    {
      "AnimLoop" : 1,
      "Animation" : 40,
      "Delay" : 4294967295,
      "RepliesList" : [ ],
      "Text" : "Now which bookshelf did I see that town portal book... I could've sworn I saw it..."
    },
    {
      "AnimLoop" : 1,
      "Animation" : 40,
      "Delay" : 4294967295,
      "RepliesList" : [ ],
      "Text" : "I wonder what the map of the stars is supposed to do..."
    },
    {
      "AnimLoop" : 1,
      "Animation" : 41,
      "Delay" : 4294967295,
      "RepliesList" : [ ],
      "Text" : "Cain doesn't know everything..."
    },
    {
      "AnimLoop" : 1,
      "Animation" : 40,
      "Delay" : 4294967295,
      "RepliesList" : [ ],
      "Text" : "I don't get it... what so important about these... these Soulstones... I have to read about it again..."
    },
    {
      "AnimLoop" : 1,
      "Animation" : 28,
      "Delay" : 4294967295,
      "RepliesList" : [ ],
      "Text" : "I don't understand what I just read..."
    },
    {
      "AnimLoop" : 1,
      "Animation" : 29,
      "Delay" : 4294967295,
      "RepliesList" : [ ],
      "Text" : "Read any good books lately?"
    }
  ],
  "NumWords" : 102,
  "PreventZoomIn" : 0,
  "ReplyList" : [ ],
  "StartingList" : [
    {
      "Active" : "rdm_oneliner1d",
      "Index" : 9
    },
    {
      "Active" : "rdm_oneliner1d",
      "Index" : 8
    },
    {
      "Active" : "rdm_oneliner1d",
      "Index" : 7
    },
    {
      "Active" : "rdm_oneliner1d",
      "Index" : 6
    },
    {
      "Active" : "rdm_oneliner1d",
      "Index" : 5
    },
    {
      "Active" : "rdm_oneliner1d",
      "Index" : 4
    },
    {
      "Active" : "rdm_oneliner1d",
      "Index" : 3
    },
    {
      "Active" : "rdm_oneliner1d",
      "Index" : 2
    },
    {
      "Active" : "rdm_oneliner1d",
      "Index" : 1
    },
    {
      "Active" : "rdm_oneliner1d",
      "Index" : 0
    }
  ]
}